rmexcept.py
runsite.py
weeaboo/__init__.py
weeaboo/app.py
weeaboo/root.arid
weeaboo/util.py
weeaboo-28.dist-info/METADATA
weeaboo-28.dist-info/WHEEL
weeaboo-28.dist-info/entry_points.txt
weeaboo-28.dist-info/top_level.txt
weeaboo-28.dist-info/RECORD
