Metadata-Version: 2.2
Name: Weeaboo
Version: 28
Summary: Shared code for websites
Home-page: https://pypi.org/project/Weeaboo/
Author: Homsar
Author-email: homsar@foyono.com
Requires-Dist: aiohttp>=3.13.2
Requires-Dist: aridity>=73
Requires-Dist: diapyr>=30
Requires-Dist: foyndation>=10
Requires-Dist: lagoon>=49
Requires-Dist: splut>=18
Requires-Dist: Werkzeug>=2.0.1
Dynamic: author
Dynamic: author-email
Dynamic: description
Dynamic: description-content-type
Dynamic: home-page
Dynamic: requires-dist
Dynamic: summary
